[
  {
    "number": 0,
    "value": -Infinity,
    "params": {
      "learning_rate": 3.502855085365447e-05,
      "n_steps": 4096,
      "batch_size": 64,
      "n_epochs": 6,
      "gamma": 0.9750851845082691,
      "gae_lambda": 0.8246165208925882,
      "clip_range": 0.14193317295062152,
      "ent_coef": 0.06226030853268707,
      "vf_coef": 0.7703477247377069,
      "max_grad_norm": 0.36429632031179426,
      "hidden_size": 512,
      "n_layers": 2,
      "lstm_hidden_size": 128,
      "n_lstm_layers": 1,
      "dropout": 0.28177533774144686,
      "risk_per_trade": 0.033612831253598124,
      "commission": 0.0010670177727709336
    },
    "user_attrs": {},
    "state": "COMPLETE"
  },
  {
    "number": 1,
    "value": -Infinity,
    "params": {
      "learning_rate": 1.6290340979602655e-05,
      "n_steps": 4096,
      "batch_size": 256,
      "n_epochs": 9,
      "gamma": 0.9491375176191056,
      "gae_lambda": 0.9045786061491251,
      "clip_range": 0.2963889656100444,
      "ent_coef": 0.0012864166609076546,
      "vf_coef": 0.8744625518108468,
      "max_grad_norm": 0.18600040849790656,
      "hidden_size": 256,
      "n_layers": 3,
      "lstm_hidden_size": 64,
      "n_lstm_layers": 3,
      "dropout": 0.2985340554802577,
      "risk_per_trade": 0.02562776485280068,
      "commission": 0.0006013166743000061
    },
    "user_attrs": {},
    "state": "COMPLETE"
  },
  {
    "number": 2,
    "value": -Infinity,
    "params": {
      "learning_rate": 0.0012238798461985288,
      "n_steps": 2048,
      "batch_size": 32,
      "n_epochs": 20,
      "gamma": 0.9104111179721803,
      "gae_lambda": 0.9214675827414757,
      "clip_range": 0.22308080631368574,
      "ent_coef": 0.008979318961355513,
      "vf_coef": 0.21094308774465065,
      "max_grad_norm": 0.17861767476897725,
      "hidden_size": 128,
      "n_layers": 2,
      "lstm_hidden_size": 128,
      "n_lstm_layers": 3,
      "dropout": 0.2960152006334847,
      "risk_per_trade": 0.04327528926372225,
      "commission": 0.0019330760363578956
    },
    "user_attrs": {},
    "state": "COMPLETE"
  },
  {
    "number": 3,
    "value": -Infinity,
    "params": {
      "learning_rate": 0.00036533438224743627,
      "n_steps": 4096,
      "batch_size": 128,
      "n_epochs": 10,
      "gamma": 0.9321767992546519,
      "gae_lambda": 0.9467716493142859,
      "clip_range": 0.12014086430875628,
      "ent_coef": 0.044783107421606363,
      "vf_coef": 0.9506473382009953,
      "max_grad_norm": 0.8436369224875936,
      "hidden_size": 512,
      "n_layers": 2,
      "lstm_hidden_size": 64,
      "n_lstm_layers": 3,
      "dropout": 0.02452184109627197,
      "risk_per_trade": 0.016429679063822183,
      "commission": 0.0014138769045393528
    },
    "user_attrs": {},
    "state": "COMPLETE"
  },
  {
    "number": 4,
    "value": -Infinity,
    "params": {
      "learning_rate": 5.994658158211818e-05,
      "n_steps": 1024,
      "batch_size": 64,
      "n_epochs": 19,
      "gamma": 0.982248872343281,
      "gae_lambda": 0.8397235998472109,
      "clip_range": 0.2870806035012988,
      "ent_coef": 0.009353781766991932,
      "vf_coef": 0.4267681302709585,
      "max_grad_norm": 0.15920887515063317,
      "hidden_size": 512,
      "n_layers": 3,
      "lstm_hidden_size": 256,
      "n_lstm_layers": 3,
      "dropout": 0.23186112358062977,
      "risk_per_trade": 0.01544733911611483,
      "commission": 0.0018763658199041037
    },
    "user_attrs": {},
    "state": "COMPLETE"
  },
  {
    "number": 5,
    "value": -Infinity,
    "params": {
      "learning_rate": 0.0005978109199118425,
      "n_steps": 1024,
      "batch_size": 64,
      "n_epochs": 16,
      "gamma": 0.9589080603380722,
      "gae_lambda": 0.9851311833664225,
      "clip_range": 0.14451017054246224,
      "ent_coef": 0.017725841821745823,
      "vf_coef": 0.6993344221449369,
      "max_grad_norm": 0.6052548465005804,
      "hidden_size": 64,
      "n_layers": 2,
      "lstm_hidden_size": 64,
      "n_lstm_layers": 2,
      "dropout": 0.20834822428114147,
      "risk_per_trade": 0.038123767445449215,
      "commission": 0.0016847391703870564
    },
    "user_attrs": {},
    "state": "COMPLETE"
  },
  {
    "number": 6,
    "value": -Infinity,
    "params": {
      "learning_rate": 0.000261929537093822,
      "n_steps": 1024,
      "batch_size": 64,
      "n_epochs": 11,
      "gamma": 0.9571449924694905,
      "gae_lambda": 0.9391246833449408,
      "clip_range": 0.21017045952922375,
      "ent_coef": 0.04426139913755825,
      "vf_coef": 0.7569303141503696,
      "max_grad_norm": 0.9528707793834964,
      "hidden_size": 512,
      "n_layers": 2,
      "lstm_hidden_size": 64,
      "n_lstm_layers": 3,
      "dropout": 0.12351172059474176,
      "risk_per_trade": 0.03099366531008208,
      "commission": 0.0007796356695395411
    },
    "user_attrs": {},
    "state": "COMPLETE"
  },
  {
    "number": 7,
    "value": -Infinity,
    "params": {
      "learning_rate": 1.207440536567111e-05,
      "n_steps": 2048,
      "batch_size": 256,
      "n_epochs": 16,
      "gamma": 0.924345911120105,
      "gae_lambda": 0.9405650472569994,
      "clip_range": 0.23162832766115318,
      "ent_coef": 0.011013295583889858,
      "vf_coef": 0.1842851637509828,
      "max_grad_norm": 0.565175511622047,
      "hidden_size": 512,
      "n_layers": 4,
      "lstm_hidden_size": 256,
      "n_lstm_layers": 1,
      "dropout": 0.22229821317162127,
      "risk_per_trade": 0.013091560786428676,
      "commission": 0.0012994024943340549
    },
    "user_attrs": {},
    "state": "COMPLETE"
  },
  {
    "number": 8,
    "value": -Infinity,
    "params": {
      "learning_rate": 0.0020029055083850326,
      "n_steps": 1024,
      "batch_size": 32,
      "n_epochs": 5,
      "gamma": 0.9782527065881386,
      "gae_lambda": 0.9200726379241968,
      "clip_range": 0.12914055866673885,
      "ent_coef": 0.0018641686090383287,
      "vf_coef": 0.4809026801059404,
      "max_grad_norm": 0.11378081376057578,
      "hidden_size": 512,
      "n_layers": 3,
      "lstm_hidden_size": 256,
      "n_lstm_layers": 1,
      "dropout": 0.09109363011036353,
      "risk_per_trade": 0.04159463299147903,
      "commission": 0.0016468755780353745
    },
    "user_attrs": {},
    "state": "COMPLETE"
  },
  {
    "number": 9,
    "value": -Infinity,
    "params": {
      "learning_rate": 1.906390485861078e-05,
      "n_steps": 1024,
      "batch_size": 64,
      "n_epochs": 6,
      "gamma": 0.9960445710649886,
      "gae_lambda": 0.9617161919335994,
      "clip_range": 0.10195572436754247,
      "ent_coef": 0.04768003659796209,
      "vf_coef": 0.2974199810393574,
      "max_grad_norm": 0.3062639973696913,
      "hidden_size": 128,
      "n_layers": 1,
      "lstm_hidden_size": 64,
      "n_lstm_layers": 2,
      "dropout": 0.14401122087689364,
      "risk_per_trade": 0.015998704509168078,
      "commission": 0.0010788305501929912
    },
    "user_attrs": {},
    "state": "COMPLETE"
  },
  {
    "number": 10,
    "value": -Infinity,
    "params": {
      "learning_rate": 0.0004516202634280199,
      "n_steps": 2048,
      "batch_size": 128,
      "n_epochs": 14,
      "gamma": 0.963188000389791,
      "gae_lambda": 0.9353464058724856,
      "clip_range": 0.1450622918293875,
      "ent_coef": 0.002362288625820729,
      "vf_coef": 0.9161899930902346,
      "max_grad_norm": 0.6886192621315097,
      "hidden_size": 64,
      "n_layers": 2,
      "lstm_hidden_size": 64,
      "n_lstm_layers": 1,
      "dropout": 0.02183292965652477,
      "risk_per_trade": 0.027452964509969043,
      "commission": 0.0006476538719579195
    },
    "user_attrs": {},
    "state": "COMPLETE"
  },
  {
    "number": 11,
    "value": -Infinity,
    "params": {
      "learning_rate": 2.239901164850589e-05,
      "n_steps": 2048,
      "batch_size": 64,
      "n_epochs": 7,
      "gamma": 0.9335098960432989,
      "gae_lambda": 0.8933128269904932,
      "clip_range": 0.2008992439521261,
      "ent_coef": 0.015060282777989133,
      "vf_coef": 0.7693337021033407,
      "max_grad_norm": 0.4271266048743061,
      "hidden_size": 128,
      "n_layers": 4,
      "lstm_hidden_size": 256,
      "n_lstm_layers": 3,
      "dropout": 0.007888531677668143,
      "risk_per_trade": 0.03497874774250272,
      "commission": 0.0006805592625252765
    },
    "user_attrs": {},
    "state": "COMPLETE"
  },
  {
    "number": 12,
    "value": -Infinity,
    "params": {
      "learning_rate": 1.1986262042183098e-05,
      "n_steps": 2048,
      "batch_size": 128,
      "n_epochs": 18,
      "gamma": 0.997099131109055,
      "gae_lambda": 0.9605539903484728,
      "clip_range": 0.11842657097406423,
      "ent_coef": 0.011498714935110543,
      "vf_coef": 0.31580719977349436,
      "max_grad_norm": 0.9652541427458149,
      "hidden_size": 512,
      "n_layers": 4,
      "lstm_hidden_size": 64,
      "n_lstm_layers": 2,
      "dropout": 0.12129213259203353,
      "risk_per_trade": 0.022055267467475347,
      "commission": 0.0009747436689899751
    },
    "user_attrs": {},
    "state": "COMPLETE"
  },
  {
    "number": 13,
    "value": -Infinity,
    "params": {
      "learning_rate": 0.0053795600493548035,
      "n_steps": 4096,
      "batch_size": 32,
      "n_epochs": 11,
      "gamma": 0.9931153207253304,
      "gae_lambda": 0.898668038701666,
      "clip_range": 0.14854265801994113,
      "ent_coef": 0.039808070950458345,
      "vf_coef": 0.6670708190439493,
      "max_grad_norm": 0.8872554719602629,
      "hidden_size": 512,
      "n_layers": 2,
      "lstm_hidden_size": 64,
      "n_lstm_layers": 1,
      "dropout": 0.1758923460362933,
      "risk_per_trade": 0.03413704500265134,
      "commission": 0.0017534793895059091
    },
    "user_attrs": {},
    "state": "COMPLETE"
  },
  {
    "number": 14,
    "value": -Infinity,
    "params": {
      "learning_rate": 0.0005149713824293737,
      "n_steps": 2048,
      "batch_size": 64,
      "n_epochs": 11,
      "gamma": 0.9019187836067487,
      "gae_lambda": 0.9544696367099742,
      "clip_range": 0.22200062891306133,
      "ent_coef": 0.003823625431942576,
      "vf_coef": 0.2547043118942966,
      "max_grad_norm": 0.7723794766451321,
      "hidden_size": 64,
      "n_layers": 1,
      "lstm_hidden_size": 256,
      "n_lstm_layers": 1,
      "dropout": 0.04548583257943595,
      "risk_per_trade": 0.02758174276216032,
      "commission": 0.0019999108227356918
    },
    "user_attrs": {},
    "state": "COMPLETE"
  },
  {
    "number": 15,
    "value": -Infinity,
    "params": {
      "learning_rate": 8.513113744001759e-05,
      "n_steps": 4096,
      "batch_size": 128,
      "n_epochs": 5,
      "gamma": 0.9919727990614255,
      "gae_lambda": 0.8012006953298685,
      "clip_range": 0.16502586625346669,
      "ent_coef": 0.09749543794730475,
      "vf_coef": 0.5911082455306623,
      "max_grad_norm": 0.3389810351005513,
      "hidden_size": 256,
      "n_layers": 1,
      "lstm_hidden_size": 128,
      "n_lstm_layers": 2,
      "dropout": 0.1695875709472955,
      "risk_per_trade": 0.04896516925977833,
      "commission": 0.0009926033347884295
    },
    "user_attrs": {},
    "state": "COMPLETE"
  },
  {
    "number": 16,
    "value": -Infinity,
    "params": {
      "learning_rate": 6.755793257347427e-05,
      "n_steps": 4096,
      "batch_size": 128,
      "n_epochs": 5,
      "gamma": 0.9953242955311971,
      "gae_lambda": 0.81303406067704,
      "clip_range": 0.16525666754575535,
      "ent_coef": 0.09802024518989305,
      "vf_coef": 0.5851379717737866,
      "max_grad_norm": 0.3239805156681933,
      "hidden_size": 256,
      "n_layers": 1,
      "lstm_hidden_size": 128,
      "n_lstm_layers": 2,
      "dropout": 0.16938170099970504,
      "risk_per_trade": 0.047815801171843315,
      "commission": 0.0009780427192271682
    },
    "user_attrs": {},
    "state": "COMPLETE"
  },
  {
    "number": 17,
    "value": -Infinity,
    "params": {
      "learning_rate": 0.0060718756883593634,
      "n_steps": 4096,
      "batch_size": 128,
      "n_epochs": 5,
      "gamma": 0.99580410636966,
      "gae_lambda": 0.80254651739285,
      "clip_range": 0.1635823162850504,
      "ent_coef": 0.08247829877829625,
      "vf_coef": 0.5911022093553666,
      "max_grad_norm": 0.37552731682055435,
      "hidden_size": 256,
      "n_layers": 1,
      "lstm_hidden_size": 128,
      "n_lstm_layers": 2,
      "dropout": 0.171949971866182,
      "risk_per_trade": 0.048045955519085595,
      "commission": 0.0009969002372308322
    },
    "user_attrs": {},
    "state": "COMPLETE"
  },
  {
    "number": 18,
    "value": -Infinity,
    "params": {
      "learning_rate": 0.008531313955761757,
      "n_steps": 4096,
      "batch_size": 256,
      "n_epochs": 8,
      "gamma": 0.988321622159779,
      "gae_lambda": 0.8073659426484597,
      "clip_range": 0.2848742049647349,
      "ent_coef": 0.08988343372692456,
      "vf_coef": 0.6403019556877034,
      "max_grad_norm": 0.32216804776430286,
      "hidden_size": 256,
      "n_layers": 1,
      "lstm_hidden_size": 128,
      "n_lstm_layers": 2,
      "dropout": 0.29502114855528766,
      "risk_per_trade": 0.02492409705038897,
      "commission": 0.000974732995046926
    },
    "user_attrs": {},
    "state": "COMPLETE"
  },
  {
    "number": 19,
    "value": -Infinity,
    "params": {
      "learning_rate": 4.457237322761679e-05,
      "n_steps": 4096,
      "batch_size": 256,
      "n_epochs": 8,
      "gamma": 0.9450221848951703,
      "gae_lambda": 0.8723232882054461,
      "clip_range": 0.29348735360155975,
      "ent_coef": 0.001038758710677541,
      "vf_coef": 0.8431373152121029,
      "max_grad_norm": 0.3496955922736669,
      "hidden_size": 256,
      "n_layers": 1,
      "lstm_hidden_size": 128,
      "n_lstm_layers": 2,
      "dropout": 0.29562813750788325,
      "risk_per_trade": 0.02465469235536625,
      "commission": 0.0010059172577249831
    },
    "user_attrs": {},
    "state": "COMPLETE"
  },
  {
    "number": 20,
    "value": -Infinity,
    "params": {
      "learning_rate": 0.007685855728105164,
      "n_steps": 4096,
      "batch_size": 256,
      "n_epochs": 9,
      "gamma": 0.9446773167938968,
      "gae_lambda": 0.8719690972979988,
      "clip_range": 0.29865742095017916,
      "ent_coef": 0.0010046242515417952,
      "vf_coef": 0.8325288264412951,
      "max_grad_norm": 0.39562716078341026,
      "hidden_size": 256,
      "n_layers": 3,
      "lstm_hidden_size": 128,
      "n_lstm_layers": 2,
      "dropout": 0.29956635187512687,
      "risk_per_trade": 0.023387616444672785,
      "commission": 0.0005090205710555993
    },
    "user_attrs": {},
    "state": "COMPLETE"
  },
  {
    "number": 21,
    "value": -Infinity,
    "params": {
      "learning_rate": 0.008254017377503649,
      "n_steps": 4096,
      "batch_size": 256,
      "n_epochs": 9,
      "gamma": 0.9437917701604763,
      "gae_lambda": 0.8771474614133974,
      "clip_range": 0.2975824557980809,
      "ent_coef": 0.00127898744120521,
      "vf_coef": 0.8630139759714378,
      "max_grad_norm": 0.3949088440776382,
      "hidden_size": 256,
      "n_layers": 3,
      "lstm_hidden_size": 128,
      "n_lstm_layers": 2,
      "dropout": 0.29447348895126474,
      "risk_per_trade": 0.023941940202051402,
      "commission": 0.000940308292070232
    },
    "user_attrs": {},
    "state": "COMPLETE"
  },
  {
    "number": 22,
    "value": -Infinity,
    "params": {
      "learning_rate": 0.009262449903588156,
      "n_steps": 4096,
      "batch_size": 256,
      "n_epochs": 9,
      "gamma": 0.9421160988746178,
      "gae_lambda": 0.8701597685578568,
      "clip_range": 0.29442265155223124,
      "ent_coef": 0.0010855180705943816,
      "vf_coef": 0.8518349681663067,
      "max_grad_norm": 0.41131857468273714,
      "hidden_size": 256,
      "n_layers": 3,
      "lstm_hidden_size": 128,
      "n_lstm_layers": 2,
      "dropout": 0.29277012613343273,
      "risk_per_trade": 0.02523216719344835,
      "commission": 0.0005202108204858826
    },
    "user_attrs": {},
    "state": "COMPLETE"
  },
  {
    "number": 23,
    "value": -Infinity,
    "params": {
      "learning_rate": 0.008739026281488467,
      "n_steps": 4096,
      "batch_size": 256,
      "n_epochs": 9,
      "gamma": 0.9428151738234394,
      "gae_lambda": 0.8746403595741703,
      "clip_range": 0.29548904782249175,
      "ent_coef": 0.0010740562208762208,
      "vf_coef": 0.8655543793557835,
      "max_grad_norm": 0.4011461690977477,
      "hidden_size": 256,
      "n_layers": 3,
      "lstm_hidden_size": 128,
      "n_lstm_layers": 2,
      "dropout": 0.2950512871351043,
      "risk_per_trade": 0.02365151995658741,
      "commission": 0.0009545626919431615
    },
    "user_attrs": {},
    "state": "COMPLETE"
  },
  {
    "number": 24,
    "value": -Infinity,
    "params": {
      "learning_rate": 0.006355121506004324,
      "n_steps": 4096,
      "batch_size": 256,
      "n_epochs": 8,
      "gamma": 0.9729053139644337,
      "gae_lambda": 0.8771417713336657,
      "clip_range": 0.2656580668305314,
      "ent_coef": 0.0011293050533654203,
      "vf_coef": 0.8423592133044604,
      "max_grad_norm": 0.39236819257017375,
      "hidden_size": 256,
      "n_layers": 3,
      "lstm_hidden_size": 128,
      "n_lstm_layers": 2,
      "dropout": 0.28494858409156265,
      "risk_per_trade": 0.024154737861707003,
      "commission": 0.0005129649839092478
    },
    "user_attrs": {},
    "state": "COMPLETE"
  },
  {
    "number": 25,
    "value": -Infinity,
    "params": {
      "learning_rate": 0.00625337806426465,
      "n_steps": 4096,
      "batch_size": 256,
      "n_epochs": 9,
      "gamma": 0.9445316926894451,
      "gae_lambda": 0.8826866352109558,
      "clip_range": 0.2916230244290643,
      "ent_coef": 0.001084988148526791,
      "vf_coef": 0.8709848508133434,
      "max_grad_norm": 0.37422118522885417,
      "hidden_size": 256,
      "n_layers": 3,
      "lstm_hidden_size": 128,
      "n_lstm_layers": 2,
      "dropout": 0.2981592949816388,
      "risk_per_trade": 0.025002220968174258,
      "commission": 0.0005292028304473114
    },
    "user_attrs": {},
    "state": "COMPLETE"
  },
  {
    "number": 26,
    "value": -Infinity,
    "params": {
      "learning_rate": 6.185461812273684e-05,
      "n_steps": 4096,
      "batch_size": 256,
      "n_epochs": 9,
      "gamma": 0.9432659061480421,
      "gae_lambda": 0.8686609125172572,
      "clip_range": 0.29765595106973997,
      "ent_coef": 0.0010294188514421926,
      "vf_coef": 0.8614686057277336,
      "max_grad_norm": 0.39262172052602273,
      "hidden_size": 256,
      "n_layers": 3,
      "lstm_hidden_size": 128,
      "n_lstm_layers": 1,
      "dropout": 0.29173536550177737,
      "risk_per_trade": 0.02493645842047044,
      "commission": 0.0005042664621258443
    },
    "user_attrs": {},
    "state": "COMPLETE"
  },
  {
    "number": 27,
    "value": -Infinity,
    "params": {
      "learning_rate": 4.712570249923854e-05,
      "n_steps": 4096,
      "batch_size": 256,
      "n_epochs": 8,
      "gamma": 0.9443197567948249,
      "gae_lambda": 0.8625100026505496,
      "clip_range": 0.2855859366561353,
      "ent_coef": 0.0010073869921720193,
      "vf_coef": 0.8565777325671631,
      "max_grad_norm": 0.43654475803345877,
      "hidden_size": 256,
      "n_layers": 3,
      "lstm_hidden_size": 128,
      "n_lstm_layers": 2,
      "dropout": 0.2893009992137505,
      "risk_per_trade": 0.023335951441895864,
      "commission": 0.000835932739196823
    },
    "user_attrs": {},
    "state": "COMPLETE"
  },
  {
    "number": 28,
    "value": -Infinity,
    "params": {
      "learning_rate": 3.360438354459653e-05,
      "n_steps": 4096,
      "batch_size": 256,
      "n_epochs": 8,
      "gamma": 0.9437352122492946,
      "gae_lambda": 0.866527815290724,
      "clip_range": 0.27723376651515874,
      "ent_coef": 0.004415959558292684,
      "vf_coef": 0.8625592732522421,
      "max_grad_norm": 0.45065173465943253,
      "hidden_size": 256,
      "n_layers": 3,
      "lstm_hidden_size": 128,
      "n_lstm_layers": 2,
      "dropout": 0.2995603901173636,
      "risk_per_trade": 0.021806190585475213,
      "commission": 0.0005600016754617695
    },
    "user_attrs": {},
    "state": "COMPLETE"
  },
  {
    "number": 29,
    "value": -Infinity,
    "params": {
      "learning_rate": 3.451965281317046e-05,
      "n_steps": 4096,
      "batch_size": 256,
      "n_epochs": 8,
      "gamma": 0.9451407583342412,
      "gae_lambda": 0.8654414855373691,
      "clip_range": 0.2851724701983003,
      "ent_coef": 0.0010736199571685027,
      "vf_coef": 0.8440764537485204,
      "max_grad_norm": 0.45553834480915145,
      "hidden_size": 256,
      "n_layers": 3,
      "lstm_hidden_size": 128,
      "n_lstm_layers": 2,
      "dropout": 0.29410445843574023,
      "risk_per_trade": 0.023168464671157997,
      "commission": 0.0005213342397858076
    },
    "user_attrs": {},
    "state": "COMPLETE"
  },
  {
    "number": 30,
    "value": -Infinity,
    "params": {
      "learning_rate": 4.3003688542190374e-05,
      "n_steps": 4096,
      "batch_size": 256,
      "n_epochs": 8,
      "gamma": 0.9459376156892203,
      "gae_lambda": 0.8597209977441682,
      "clip_range": 0.27542091258623447,
      "ent_coef": 0.001181965538327324,
      "vf_coef": 0.8783205267801253,
      "max_grad_norm": 0.4495549674823622,
      "hidden_size": 256,
      "n_layers": 3,
      "lstm_hidden_size": 128,
      "n_lstm_layers": 2,
      "dropout": 0.2996511469746171,
      "risk_per_trade": 0.022634919906614568,
      "commission": 0.0005599695793036889
    },
    "user_attrs": {},
    "state": "COMPLETE"
  },
  {
    "number": 31,
    "value": -Infinity,
    "params": {
      "learning_rate": 3.5361652751600746e-05,
      "n_steps": 4096,
      "batch_size": 256,
      "n_epochs": 8,
      "gamma": 0.9712965707356711,
      "gae_lambda": 0.8631427178516162,
      "clip_range": 0.27737462260073337,
      "ent_coef": 0.004354008175953608,
      "vf_coef": 0.8578586950041565,
      "max_grad_norm": 0.4242417960839411,
      "hidden_size": 256,
      "n_layers": 3,
      "lstm_hidden_size": 128,
      "n_lstm_layers": 2,
      "dropout": 0.2962018228226359,
      "risk_per_trade": 0.023898970442877056,
      "commission": 0.0005120203423889117
    },
    "user_attrs": {},
    "state": "COMPLETE"
  },
  {
    "number": 32,
    "value": -Infinity,
    "params": {
      "learning_rate": 3.934846223314194e-05,
      "n_steps": 4096,
      "batch_size": 256,
      "n_epochs": 8,
      "gamma": 0.9462415597117261,
      "gae_lambda": 0.8651417356747206,
      "clip_range": 0.29211593699219845,
      "ent_coef": 0.0010781279430960415,
      "vf_coef": 0.8654578201520075,
      "max_grad_norm": 0.470166526445739,
      "hidden_size": 256,
      "n_layers": 3,
      "lstm_hidden_size": 128,
      "n_lstm_layers": 2,
      "dropout": 0.2820155173616935,
      "risk_per_trade": 0.02228070911238425,
      "commission": 0.000515204710829309
    },
    "user_attrs": {},
    "state": "COMPLETE"
  },
  {
    "number": 33,
    "value": -Infinity,
    "params": {
      "learning_rate": 3.774818599372925e-05,
      "n_steps": 4096,
      "batch_size": 256,
      "n_epochs": 8,
      "gamma": 0.9464101522939454,
      "gae_lambda": 0.8601129922090854,
      "clip_range": 0.2560850255752169,
      "ent_coef": 0.0012579281744764714,
      "vf_coef": 0.8616309462404139,
      "max_grad_norm": 0.4606430655216861,
      "hidden_size": 256,
      "n_layers": 3,
      "lstm_hidden_size": 128,
      "n_lstm_layers": 3,
      "dropout": 0.29844358638642765,
      "risk_per_trade": 0.022186119636220122,
      "commission": 0.0005681103232487396
    },
    "user_attrs": {},
    "state": "COMPLETE"
  },
  {
    "number": 34,
    "value": -Infinity,
    "params": {
      "learning_rate": 0.0001501136084564136,
      "n_steps": 4096,
      "batch_size": 256,
      "n_epochs": 13,
      "gamma": 0.9707387578392866,
      "gae_lambda": 0.8525671349634615,
      "clip_range": 0.25510332479845726,
      "ent_coef": 0.00382897903851419,
      "vf_coef": 0.8605295810498301,
      "max_grad_norm": 0.4950892054601468,
      "hidden_size": 256,
      "n_layers": 3,
      "lstm_hidden_size": 128,
      "n_lstm_layers": 1,
      "dropout": 0.2560057706983355,
      "risk_per_trade": 0.020588557147901858,
      "commission": 0.0014776178477502533
    },
    "user_attrs": {},
    "state": "COMPLETE"
  },
  {
    "number": 35,
    "value": -Infinity,
    "params": {
      "learning_rate": 0.00013489789948371034,
      "n_steps": 4096,
      "batch_size": 256,
      "n_epochs": 13,
      "gamma": 0.9709691458893447,
      "gae_lambda": 0.8599040942723266,
      "clip_range": 0.25499589206957884,
      "ent_coef": 0.0037164594498255445,
      "vf_coef": 0.9949990794798229,
      "max_grad_norm": 0.24567001177192427,
      "hidden_size": 256,
      "n_layers": 3,
      "lstm_hidden_size": 128,
      "n_lstm_layers": 3,
      "dropout": 0.2571092608804443,
      "risk_per_trade": 0.032219979624953994,
      "commission": 0.0014536525754236405
    },
    "user_attrs": {},
    "state": "COMPLETE"
  },
  {
    "number": 36,
    "value": -Infinity,
    "params": {
      "learning_rate": 0.0013282431940925125,
      "n_steps": 2048,
      "batch_size": 32,
      "n_epochs": 13,
      "gamma": 0.9078800991390511,
      "gae_lambda": 0.9136157671217059,
      "clip_range": 0.26089595443786523,
      "ent_coef": 0.006558080977909315,
      "vf_coef": 0.41938339497257665,
      "max_grad_norm": 0.22560253076079223,
      "hidden_size": 128,
      "n_layers": 3,
      "lstm_hidden_size": 128,
      "n_lstm_layers": 3,
      "dropout": 0.2628855085254856,
      "risk_per_trade": 0.04190504202466617,
      "commission": 0.0014565180596904977
    },
    "user_attrs": {},
    "state": "COMPLETE"
  },
  {
    "number": 37,
    "value": -Infinity,
    "params": {
      "learning_rate": 0.00014721182723841474,
      "n_steps": 2048,
      "batch_size": 32,
      "n_epochs": 13,
      "gamma": 0.906502679985727,
      "gae_lambda": 0.8472503436469608,
      "clip_range": 0.2493736072269908,
      "ent_coef": 0.006267175730303704,
      "vf_coef": 0.9957128464716218,
      "max_grad_norm": 0.21212151327103038,
      "hidden_size": 128,
      "n_layers": 2,
      "lstm_hidden_size": 128,
      "n_lstm_layers": 3,
      "dropout": 0.2616105147857103,
      "risk_per_trade": 0.04119521884097487,
      "commission": 0.0013710850946548913
    },
    "user_attrs": {},
    "state": "COMPLETE"
  },
  {
    "number": 38,
    "value": -Infinity,
    "params": {
      "learning_rate": 0.001456554879186166,
      "n_steps": 2048,
      "batch_size": 32,
      "n_epochs": 13,
      "gamma": 0.90065223541432,
      "gae_lambda": 0.9159026217014249,
      "clip_range": 0.2499981079963074,
      "ent_coef": 0.005865441483214056,
      "vf_coef": 0.9987268695019783,
      "max_grad_norm": 0.19624029752319522,
      "hidden_size": 128,
      "n_layers": 2,
      "lstm_hidden_size": 128,
      "n_lstm_layers": 3,
      "dropout": 0.25697402376414413,
      "risk_per_trade": 0.04228426443491752,
      "commission": 0.0014655495404685213
    },
    "user_attrs": {},
    "state": "COMPLETE"
  },
  {
    "number": 39,
    "value": -Infinity,
    "params": {
      "learning_rate": 0.000162699828429543,
      "n_steps": 2048,
      "batch_size": 32,
      "n_epochs": 13,
      "gamma": 0.9021370115520126,
      "gae_lambda": 0.8492273475931312,
      "clip_range": 0.2460810666251651,
      "ent_coef": 0.005498602566559981,
      "vf_coef": 0.9758638003684748,
      "max_grad_norm": 0.2208545286279763,
      "hidden_size": 128,
      "n_layers": 2,
      "lstm_hidden_size": 128,
      "n_lstm_layers": 3,
      "dropout": 0.25277572235334334,
      "risk_per_trade": 0.04142064223042724,
      "commission": 0.0014823804244903111
    },
    "user_attrs": {},
    "state": "COMPLETE"
  },
  {
    "number": 40,
    "value": -Infinity,
    "params": {
      "learning_rate": 0.00015101116718474808,
      "n_steps": 2048,
      "batch_size": 32,
      "n_epochs": 14,
      "gamma": 0.9172702625560366,
      "gae_lambda": 0.9149122522762085,
      "clip_range": 0.24630559692543938,
      "ent_coef": 0.0047554585043772845,
      "vf_coef": 0.9993598225626181,
      "max_grad_norm": 0.21504696234093013,
      "hidden_size": 128,
      "n_layers": 2,
      "lstm_hidden_size": 64,
      "n_lstm_layers": 3,
      "dropout": 0.2610633092680241,
      "risk_per_trade": 0.04299554275355165,
      "commission": 0.001203546292529534
    },
    "user_attrs": {},
    "state": "COMPLETE"
  },
  {
    "number": 41,
    "value": -Infinity,
    "params": {
      "learning_rate": 0.00013212830488659518,
      "n_steps": 2048,
      "batch_size": 32,
      "n_epochs": 14,
      "gamma": 0.9006823988742322,
      "gae_lambda": 0.9124967583854405,
      "clip_range": 0.2495327535641862,
      "ent_coef": 0.006345066178937209,
      "vf_coef": 0.11241646062457379,
      "max_grad_norm": 0.18835848540554442,
      "hidden_size": 128,
      "n_layers": 2,
      "lstm_hidden_size": 64,
      "n_lstm_layers": 3,
      "dropout": 0.25475081354619067,
      "risk_per_trade": 0.03813821399635944,
      "commission": 0.0014120006765139786
    },
    "user_attrs": {},
    "state": "COMPLETE"
  },
  {
    "number": 42,
    "value": -Infinity,
    "params": {
      "learning_rate": 0.00016962055141786126,
      "n_steps": 2048,
      "batch_size": 32,
      "n_epochs": 20,
      "gamma": 0.9134016297946769,
      "gae_lambda": 0.9144614319832265,
      "clip_range": 0.2562770427470885,
      "ent_coef": 0.027310164381501592,
      "vf_coef": 0.9891705324391464,
      "max_grad_norm": 0.23498737513637724,
      "hidden_size": 128,
      "n_layers": 2,
      "lstm_hidden_size": 64,
      "n_lstm_layers": 3,
      "dropout": 0.25636738536521214,
      "risk_per_trade": 0.01850363560648273,
      "commission": 0.0014222655295303044
    },
    "user_attrs": {},
    "state": "COMPLETE"
  },
  {
    "number": 43,
    "value": -Infinity,
    "params": {
      "learning_rate": 0.0001928148829114784,
      "n_steps": 2048,
      "batch_size": 32,
      "n_epochs": 20,
      "gamma": 0.9140573539133287,
      "gae_lambda": 0.9177637327855046,
      "clip_range": 0.2560644924270558,
      "ent_coef": 0.026208184114111,
      "vf_coef": 0.9849090211527961,
      "max_grad_norm": 0.2079943005853367,
      "hidden_size": 128,
      "n_layers": 2,
      "lstm_hidden_size": 64,
      "n_lstm_layers": 3,
      "dropout": 0.25749228324591195,
      "risk_per_trade": 0.018075336283452925,
      "commission": 0.0014498267381497219
    },
    "user_attrs": {},
    "state": "COMPLETE"
  },
  {
    "number": 44,
    "value": -Infinity,
    "params": {
      "learning_rate": 0.00013400080222875755,
      "n_steps": 2048,
      "batch_size": 32,
      "n_epochs": 19,
      "gamma": 0.9139462649557735,
      "gae_lambda": 0.9086524806535553,
      "clip_range": 0.24862076503680752,
      "ent_coef": 0.025453935098336333,
      "vf_coef": 0.9952503362823591,
      "max_grad_norm": 0.22584836952513795,
      "hidden_size": 128,
      "n_layers": 2,
      "lstm_hidden_size": 64,
      "n_lstm_layers": 3,
      "dropout": 0.25749061247175575,
      "risk_per_trade": 0.04199027067026312,
      "commission": 0.0013063247115804285
    },
    "user_attrs": {},
    "state": "COMPLETE"
  },
  {
    "number": 45,
    "value": -Infinity,
    "params": {
      "learning_rate": 0.00016288084710957632,
      "n_steps": 2048,
      "batch_size": 32,
      "n_epochs": 12,
      "gamma": 0.9145168915652735,
      "gae_lambda": 0.9097757015752952,
      "clip_range": 0.1827720842564065,
      "ent_coef": 0.030872339943721596,
      "vf_coef": 0.9836327666475465,
      "max_grad_norm": 0.23459383370023051,
      "hidden_size": 128,
      "n_layers": 2,
      "lstm_hidden_size": 64,
      "n_lstm_layers": 3,
      "dropout": 0.260407473959839,
      "risk_per_trade": 0.017964368188209116,
      "commission": 0.001405875138385837
    },
    "user_attrs": {},
    "state": "COMPLETE"
  },
  {
    "number": 46,
    "value": -Infinity,
    "params": {
      "learning_rate": 0.0001441992755025226,
      "n_steps": 2048,
      "batch_size": 32,
      "n_epochs": 20,
      "gamma": 0.9101381787252274,
      "gae_lambda": 0.9110392732601593,
      "clip_range": 0.24075406818449163,
      "ent_coef": 0.022693153292137218,
      "vf_coef": 0.9872299747649173,
      "max_grad_norm": 0.1979392593057744,
      "hidden_size": 128,
      "n_layers": 2,
      "lstm_hidden_size": 64,
      "n_lstm_layers": 3,
      "dropout": 0.2594922269896308,
      "risk_per_trade": 0.04118413921494686,
      "commission": 0.0014276343671307031
    },
    "user_attrs": {},
    "state": "COMPLETE"
  },
  {
    "number": 47,
    "value": -Infinity,
    "params": {
      "learning_rate": 0.00017136247496447342,
      "n_steps": 2048,
      "batch_size": 32,
      "n_epochs": 13,
      "gamma": 0.9112283757958064,
      "gae_lambda": 0.9166973532571681,
      "clip_range": 0.2460690620652326,
      "ent_coef": 0.030949922248227933,
      "vf_coef": 0.9500333981499177,
      "max_grad_norm": 0.21567950015098192,
      "hidden_size": 128,
      "n_layers": 2,
      "lstm_hidden_size": 64,
      "n_lstm_layers": 3,
      "dropout": 0.2554977392092106,
      "risk_per_trade": 0.017469341420029226,
      "commission": 0.0014264701716826334
    },
    "user_attrs": {},
    "state": "COMPLETE"
  },
  {
    "number": 48,
    "value": -Infinity,
    "params": {
      "learning_rate": 0.0001235084316241233,
      "n_steps": 2048,
      "batch_size": 32,
      "n_epochs": 20,
      "gamma": 0.9177944782270642,
      "gae_lambda": 0.9081746122898381,
      "clip_range": 0.25349174526271906,
      "ent_coef": 0.029270861352074178,
      "vf_coef": 0.9743259067470841,
      "max_grad_norm": 0.22524211383998477,
      "hidden_size": 128,
      "n_layers": 2,
      "lstm_hidden_size": 64,
      "n_lstm_layers": 3,
      "dropout": 0.2541476493422519,
      "risk_per_trade": 0.01834725720821799,
      "commission": 0.0013734969556931744
    },
    "user_attrs": {},
    "state": "COMPLETE"
  },
  {
    "number": 49,
    "value": -Infinity,
    "params": {
      "learning_rate": 0.0001481256818368117,
      "n_steps": 2048,
      "batch_size": 32,
      "n_epochs": 20,
      "gamma": 0.9124468042955,
      "gae_lambda": 0.9135790263185868,
      "clip_range": 0.1826764365590297,
      "ent_coef": 0.02577729849851855,
      "vf_coef": 0.9824336636666053,
      "max_grad_norm": 0.2647459622862067,
      "hidden_size": 128,
      "n_layers": 2,
      "lstm_hidden_size": 64,
      "n_lstm_layers": 3,
      "dropout": 0.25501684795934826,
      "risk_per_trade": 0.041885476453781476,
      "commission": 0.001412474178227513
    },
    "user_attrs": {},
    "state": "COMPLETE"
  }
]